chitose/__init__.py
chitose/agent.py
chitose/app/__init__.py
chitose/app/bsky/__init__.py
chitose/app/bsky/actor/__init__.py
chitose/app/bsky/actor/defs.py
chitose/app/bsky/actor/get_preferences.py
chitose/app/bsky/actor/get_profile.py
chitose/app/bsky/actor/get_profiles.py
chitose/app/bsky/actor/get_suggestions.py
chitose/app/bsky/actor/profile.py
chitose/app/bsky/actor/put_preferences.py
chitose/app/bsky/actor/search_actors.py
chitose/app/bsky/actor/search_actors_typeahead.py
chitose/app/bsky/embed/__init__.py
chitose/app/bsky/embed/external.py
chitose/app/bsky/embed/images.py
chitose/app/bsky/embed/record.py
chitose/app/bsky/embed/record_with_media.py
chitose/app/bsky/feed/__init__.py
chitose/app/bsky/feed/defs.py
chitose/app/bsky/feed/describe_feed_generator.py
chitose/app/bsky/feed/generator.py
chitose/app/bsky/feed/get_actor_feeds.py
chitose/app/bsky/feed/get_actor_likes.py
chitose/app/bsky/feed/get_author_feed.py
chitose/app/bsky/feed/get_feed.py
chitose/app/bsky/feed/get_feed_generator.py
chitose/app/bsky/feed/get_feed_generators.py
chitose/app/bsky/feed/get_feed_skeleton.py
chitose/app/bsky/feed/get_likes.py
chitose/app/bsky/feed/get_list_feed.py
chitose/app/bsky/feed/get_post_thread.py
chitose/app/bsky/feed/get_posts.py
chitose/app/bsky/feed/get_reposted_by.py
chitose/app/bsky/feed/get_suggested_feeds.py
chitose/app/bsky/feed/get_timeline.py
chitose/app/bsky/feed/like.py
chitose/app/bsky/feed/post.py
chitose/app/bsky/feed/repost.py
chitose/app/bsky/feed/threadgate.py
chitose/app/bsky/graph/__init__.py
chitose/app/bsky/graph/block.py
chitose/app/bsky/graph/defs.py
chitose/app/bsky/graph/follow.py
chitose/app/bsky/graph/get_blocks.py
chitose/app/bsky/graph/get_followers.py
chitose/app/bsky/graph/get_follows.py
chitose/app/bsky/graph/get_list.py
chitose/app/bsky/graph/get_list_blocks.py
chitose/app/bsky/graph/get_list_mutes.py
chitose/app/bsky/graph/get_lists.py
chitose/app/bsky/graph/get_mutes.py
chitose/app/bsky/graph/get_suggested_follows_by_actor.py
chitose-0.0.11.dist-info/LICENSE
chitose-0.0.11.dist-info/METADATA
chitose-0.0.11.dist-info/WHEEL
chitose-0.0.11.dist-info/RECORD
