Metadata-Version: 2.1
Name: chitose
Version: 0.0.11
Summary: A client library for the AT Protocol (Bluesky) 
Home-page: https://github.com/mnogu/chitose
License: MIT
Author: Muneyuki Noguchi
Author-email: nogu.dev@gmail.com
Requires-Python: >=3.9
Classifier: Development Status :: 3 - Alpha
Classifier: License :: OSI Approved :: MIT License
Classifier: Operating System :: OS Independent
Classifier: Programming Language :: Python :: 3
Classifier: Programming Language :: Python :: 3.9
Classifier: Programming Language :: Python :: 3.10
Classifier: Programming Language :: Python :: 3.11
Classifier: Topic :: Documentation :: Sphinx
Requires-Dist: websockets (>=11.0)
Project-URL: Documentation, https://chitose.readthedocs.io/en/latest/
Project-URL: Repository, https://github.com/mnogu/chitose
